DatasetBuilder.py
ImgDatasetBuilder-1.0.2.dist-info/LICENSE.txt
ImgDatasetBuilder-1.0.2.dist-info/METADATA
ImgDatasetBuilder-1.0.2.dist-info/WHEEL
ImgDatasetBuilder-1.0.2.dist-info/top_level.txt
ImgDatasetBuilder-1.0.2.dist-info/RECORD
