Metadata-Version: 2.1
Name: ImgDatasetBuilder
Version: 1.0.2
Summary: Build an image dataset with your webcam
Home-page: https://github.com/YnsOzt/Image_Dataset_Builder
Author: Sakir Ozturk
Author-email: ozturk213@hotmail.fr
License: UNKNOWN
Platform: UNKNOWN
Requires-Dist: opencv-python (>=4.2.0)
